{
  "gitSyncId": "685bb5983f26b764835f01ec_d8d87489-cb57-4d26-90b5-e6bfb831c747",
  "id": "Page1_Query1",
  "pluginId": "mongo-plugin",
  "pluginType": "DB",
  "unpublishedAction": {
    "actionConfiguration": {
      "encodeParamsToggle": true,
      "formData": {
        "aggregate": {
          "arrayPipelines": {
            "data": ""
          },
          "limit": {
            "data": "10"
          }
        },
        "body": {
          "data": "{\n  \"find\": \"movies\",\n  \"filter\": {\n    \"homepage\": \"https://movies.disney.com/cruella\"\n  },\n  \"sort\": {\n    \"_id\": 1\n  },\n  \"limit\": 10\n}\n"
        },
        "collection": {
          "data": "movies"
        },
        "command": {
          "data": "FIND"
        },
        "count": {
          "query": {
            "data": ""
          }
        },
        "delete": {
          "limit": {
            "data": "SINGLE"
          },
          "query": {
            "data": ""
          }
        },
        "distinct": {
          "key": {
            "data": ""
          },
          "query": {
            "data": ""
          }
        },
        "find": {
          "limit": {
            "data": "10"
          },
          "projection": {
            "data": ""
          },
          "query": {
            "data": "{ \"homepage\": \"https://movies.disney.com/cruella\"}"
          },
          "skip": {
            "data": ""
          },
          "sort": {
            "data": "{\"_id\": 1}"
          }
        },
        "insert": {
          "documents": {
            "data": ""
          }
        },
        "smartSubstitution": {
          "data": true
        },
        "updateMany": {
          "limit": {
            "data": "SINGLE"
          },
          "query": {
            "data": ""
          },
          "update": {
            "data": ""
          }
        }
      },
      "paginationType": "NONE",
      "timeoutInMillisecond": 10000
    },
    "confirmBeforeExecute": false,
    "datasource": {
      "id": "Movies",
      "isAutoGenerated": false,
      "name": "Movies",
      "pluginId": "mongo-plugin"
    },
    "dynamicBindingPathList": [],
    "name": "Query1",
    "pageId": "Page1",
    "runBehaviour": "AUTOMATIC",
    "userSetOnLoad": true
  }
}